abx24/__init__.py
abx24/bitrix24.py
abx24/exceptions.py
tests/__init__.py
tests/test_bitrix24.py
abx24-1.1.2.dist-info/LICENSE
abx24-1.1.2.dist-info/METADATA
abx24-1.1.2.dist-info/WHEEL
abx24-1.1.2.dist-info/top_level.txt
abx24-1.1.2.dist-info/RECORD
